{
  "label": "Volume 4",
  "words": [
    "Combine Harvester",
    "Komodo Dragon",
    "Puffin",
    "Glyptodon",
    "Stalagmite",
    "Trebuchet",
    "Clownfish",
    "Gorilla",
    "Penguin",
    "Megatherium",
    "Abacus",
    "Humpback Whale",
    "Mandrill",
    "Sea Lion",
    "Propeller",
    "Tapir",
    "Lobster",
    "Satellite",
    "Okapi",
    "Octopus",
    "Lute",
    "Jaguar",
    "Nautilus",
    "Crossbow",
    "Hyena",
    "Blue Marlin",
    "Katana",
    "Warthog",
    "Sea Snake",
    "Skeleton",
    "Moose",
    "Dugong",
    "Oboe",
    "Macaw",
    "Porpoise",
    "Mandolin",
    "Toucan",
    "Pelican",
    "Hang Glider",
    "Hornbill",
    "Tarantula",
    "Drone",
    "Condor",
    "Fossa",
    "Dirt Bike",
    "Harpy Eagle",
    "Numbat",
    "Penny-farthing",
    "Secretary Bird",
    "Ibex"
  ],
  "wikiTerms": {
    "Combine Harvester": "Combine harvester",
    "Komodo Dragon": "Komodo dragon",
    "Harpy Eagle": "Harpy eagle",
    "Secretary Bird": "Secretarybird",
    "Humpback Whale": "Humpback whale",
    "Blue Marlin": "Blue marlin",
    "Sea Snake": "Sea snake",
    "Sea Lion": "Sea lion",
    "Hang Glider": "Hang gliding",
    "Penny-farthing": "Penny-farthing",
    "Glyptodon": "Glyptodon",
    "Megatherium": "Megatherium"
  }
}
